graphtik/__init__.py
graphtik/base.py
graphtik/config.py
graphtik/execution.py
graphtik/fnop.py
graphtik/jetsam.py
graphtik/jsonpointer.py
graphtik/modifier.py
graphtik/pipeline.py
graphtik/planning.py
graphtik/plot.py
graphtik/sphinxext/__init__.py
graphtik/sphinxext/_graphtikbuilder.py
graphtik/sphinxext/doctestglobs.py
graphtik/sphinxext/graphtik.css
graphtik-10.5.0.dist-info/LICENSE
graphtik-10.5.0.dist-info/METADATA
graphtik-10.5.0.dist-info/WHEEL
graphtik-10.5.0.dist-info/top_level.txt
graphtik-10.5.0.dist-info/zip-safe
graphtik-10.5.0.dist-info/RECORD
