Metadata-Version: 2.1
Name: graphtik
Version: 10.5.0
Summary: A Python lib for solving & executing graphs of functions, with `pandas` in mind
Home-page: http://github.com/pygraphkit/graphtik
Author: Kostis Anagnostopoulos, Huy Nguyen, Arel Cordero, Pierre Garrigues, Rob Hess, Tobi Baumgartner, Clayton Mellina
Author-email: ankostis@gmail.com
License: Apache-2.0
Project-URL: Documentation, https://graphtik.readthedocs.io/
Project-URL: Release Notes, https://graphtik.readthedocs.io/en/latest/changes.html
Project-URL: Sources, https://github.com/pygraphkit/graphtik
Project-URL: Bug Tracker, https://github.com/pygraphkit/graphtik/issues
Keywords: graph,computation graph,DAG,directed acyclic graph,executor,scheduler,etl,workflow,pipeline
Platform: Windows
Platform: Linux
Platform: Solaris
Platform: Mac OS-X
Platform: Unix
Classifier: Development Status :: 4 - Beta
Classifier: License :: OSI Approved :: Apache Software License
Classifier: Intended Audience :: Developers
Classifier: Intended Audience :: Science/Research
Classifier: Natural Language :: English
Classifier: Operating System :: MacOS :: MacOS X
Classifier: Operating System :: Microsoft :: Windows
Classifier: Operating System :: OS Independent
Classifier: Operating System :: POSIX
Classifier: Operating System :: Unix
Classifier: Programming Language :: Python
Classifier: Programming Language :: Python :: 3.6
Classifier: Programming Language :: Python :: 3.7
Classifier: Programming Language :: Python :: 3.8
Classifier: Topic :: Software Development :: Libraries
Classifier: Topic :: Software Development :: Libraries :: Python Modules
Classifier: Topic :: Scientific/Engineering
Classifier: Topic :: Software Development
Requires-Python: >=3.6
License-File: LICENSE
Requires-Dist: boltons
Requires-Dist: networkx (==2.2) ; python_version < "3.5"
Requires-Dist: contextvars ; python_version < "3.7"
Requires-Dist: dataclasses ; python_version < "3.7"
Requires-Dist: networkx ; python_version >= "3.5"
Provides-Extra: all
Requires-Dist: pydot ; extra == 'all'
Requires-Dist: html5lib ; extra == 'all'
Requires-Dist: pandas ; extra == 'all'
Requires-Dist: pytest-sugar ; extra == 'all'
Requires-Dist: sphinxcontrib-spelling ; extra == 'all'
Requires-Dist: matplotlib ; extra == 'all'
Requires-Dist: sphinx[setuptools] (>=2) ; extra == 'all'
Requires-Dist: pytest-cov ; extra == 'all'
Requires-Dist: MarkupSafe ; extra == 'all'
Requires-Dist: pytest ; extra == 'all'
Requires-Dist: pytest-sphinx (>=0.2.1) ; extra == 'all'
Requires-Dist: jinja2 (>=3) ; extra == 'all'
Requires-Dist: readme-renderer ; extra == 'all'
Requires-Dist: dill ; extra == 'all'
Requires-Dist: wheel ; extra == 'all'
Requires-Dist: black ; extra == 'all'
Requires-Dist: pylint ; extra == 'all'
Requires-Dist: mypy ; extra == 'all'
Requires-Dist: importlib-resources ; (python_version < "3.7") and extra == 'all'
Provides-Extra: dev
Requires-Dist: pydot ; extra == 'dev'
Requires-Dist: html5lib ; extra == 'dev'
Requires-Dist: pandas ; extra == 'dev'
Requires-Dist: pytest-sugar ; extra == 'dev'
Requires-Dist: sphinxcontrib-spelling ; extra == 'dev'
Requires-Dist: matplotlib ; extra == 'dev'
Requires-Dist: sphinx[setuptools] (>=2) ; extra == 'dev'
Requires-Dist: pytest-cov ; extra == 'dev'
Requires-Dist: MarkupSafe ; extra == 'dev'
Requires-Dist: pytest ; extra == 'dev'
Requires-Dist: pytest-sphinx (>=0.2.1) ; extra == 'dev'
Requires-Dist: jinja2 (>=3) ; extra == 'dev'
Requires-Dist: readme-renderer ; extra == 'dev'
Requires-Dist: dill ; extra == 'dev'
Requires-Dist: wheel ; extra == 'dev'
Requires-Dist: black ; extra == 'dev'
Requires-Dist: pylint ; extra == 'dev'
Requires-Dist: mypy ; extra == 'dev'
Requires-Dist: importlib-resources ; (python_version < "3.7") and extra == 'dev'
Provides-Extra: dill
Requires-Dist: dill ; extra == 'dill'
Provides-Extra: matplot
Requires-Dist: pydot ; extra == 'matplot'
Requires-Dist: jinja2 (>=3) ; extra == 'matplot'
Requires-Dist: MarkupSafe ; extra == 'matplot'
Requires-Dist: matplotlib ; extra == 'matplot'
Requires-Dist: importlib-resources ; (python_version < "3.7") and extra == 'matplot'
Provides-Extra: plot
Requires-Dist: pydot ; extra == 'plot'
Requires-Dist: jinja2 (>=3) ; extra == 'plot'
Requires-Dist: MarkupSafe ; extra == 'plot'
Requires-Dist: importlib-resources ; (python_version < "3.7") and extra == 'plot'
Provides-Extra: sphinx
Requires-Dist: pydot ; extra == 'sphinx'
Requires-Dist: jinja2 (>=3) ; extra == 'sphinx'
Requires-Dist: MarkupSafe ; extra == 'sphinx'
Requires-Dist: sphinx[setuptools] (>=2) ; extra == 'sphinx'
Requires-Dist: importlib-resources ; (python_version < "3.7") and extra == 'sphinx'
Provides-Extra: test
Requires-Dist: pydot ; extra == 'test'
Requires-Dist: html5lib ; extra == 'test'
Requires-Dist: pandas ; extra == 'test'
Requires-Dist: pytest-sugar ; extra == 'test'
Requires-Dist: sphinxcontrib-spelling ; extra == 'test'
Requires-Dist: matplotlib ; extra == 'test'
Requires-Dist: sphinx[setuptools] (>=2) ; extra == 'test'
Requires-Dist: pytest-cov ; extra == 'test'
Requires-Dist: MarkupSafe ; extra == 'test'
Requires-Dist: pytest ; extra == 'test'
Requires-Dist: pytest-sphinx (>=0.2.1) ; extra == 'test'
Requires-Dist: jinja2 (>=3) ; extra == 'test'
Requires-Dist: readme-renderer ; extra == 'test'
Requires-Dist: dill ; extra == 'test'
Requires-Dist: importlib-resources ; (python_version < "3.7") and extra == 'test'
